simples_calculadora/__init__.py
simples_calculadora/simples_calculadora.py
simples_calculadora-0.0.1.dist-info/METADATA
simples_calculadora-0.0.1.dist-info/WHEEL
simples_calculadora-0.0.1.dist-info/top_level.txt
simples_calculadora-0.0.1.dist-info/RECORD
