Metadata-Version: 2.1
Name: simples-calculadora
Version: 0.0.1
Summary: Pacote de uma simples calculadora
Home-page: https://github.com/DiegoReis265/Repositorio-BootCamp-Geracao-Tech-Unimed-BH--Ciencia-de-Dados.git
Author: Diego Reis
Author-email: d.felipe66@yahoo.com
License: UNKNOWN
Platform: UNKNOWN
Requires-Python: >=3.8
